{
	"miniprogramRoot": "dist/",
	"projectname": "taro-booking-scan-end",
	"description": "",
	"appid": "wxde7f6ac3644260a1",
	"setting": {
		"urlCheck": false,
		"es6": false,
		"postcss": false,
		"minified": false,
		"newFeature": true,
		"coverView": true,
		"autoAudits": false,
		"checkInvalidKey": true,
		"checkSiteMap": true,
		"uploadWithSourceMap": true,
		"babelSetting": {
			"ignore": [],
			"disablePlugins": [],
			"outputPath": ""
		}
	},
	"compileType": "miniprogram",
	"simulatorType": "wechat",
	"simulatorPluginLibVersion": {},
	"condition": {}
}
